{"cameraMode":{"drawMode":0,"name":"Shaded","section":"Shading Mode"},"sceneLighting":true,"audioPlay":false,"sceneViewState":{"m_AlwaysRefresh":false,"showFog":true,"showSkybox":true,"showFlares":true,"showImageEffects":true,"showParticleSystems":true,"showVisualEffectGraphs":true,"m_FxEnabled":true},"in2DMode":false,"pivot":{"x":-18.36142921447754,"y":2.167468547821045,"z":-12.464423179626465},"rotation":{"x":0.27980583906173708,"y":0.1959088295698166,"z":-0.05835816636681557,"w":0.938249945640564},"size":4.635643482208252,"orthographic":false}